{
  "version": "1.1.1",
  "windows": {
    "main": {
      "main": true,
      "url": "app://editor/index.html",
      "windowType": "dockable",
      "x": -1920,
      "y": -268,
      "width": 1920,
      "height": 1032,
      "layout": {
        "type": "dock-h",
        "children": [
          {
            "width": 303.4375,
            "height": 914,
            "type": "dock-v",
            "children": [
              {
                "width": 303.4375,
                "height": 457.953125,
                "type": "panel",
                "active": 0,
                "children": [
                  "hierarchy"
                ]
              },
              {
                "width": 303.4375,
                "height": 453.046875,
                "type": "panel",
                "active": 0,
                "children": [
                  "assets"
                ]
              }
            ]
          },
          {
            "width": 1080.890625,
            "height": 914,
            "type": "dock-v",
            "children": [
              {
                "width": 1080.890625,
                "height": 645,
                "type": "panel",
                "active": 0,
                "children": [
                  "scene"
                ]
              },
              {
                "width": 1080.890625,
                "height": 266,
                "type": "panel",
                "active": 0,
                "children": [
                  "console",
                  "timeline",
                  "game-window"
                ]
              }
            ]
          },
          {
            "width": 513.671875,
            "height": 914,
            "type": "panel",
            "active": 0,
            "children": [
              "inspector",
              "cocos-services"
            ]
          }
        ]
      },
      "panels": [
        "hierarchy",
        "assets",
        "scene",
        "console",
        "timeline",
        "game-window",
        "inspector",
        "cocos-services"
      ]
    },
    "window-1655750274058": {}
  },
  "panels": {
    "project-settings": {
      "x": 216,
      "y": 84,
      "width": 608,
      "height": 572
    },
    "builder": {
      "x": 416,
      "y": 72,
      "width": 520,
      "height": 740
    }
  },
  "panelLabelWidth": {}
}
