{
  "version": "1.1.1",
  "windows": {
    "main": {
      "main": true,
      "url": "app://editor/index.html",
      "windowType": "dockable",
      "x": 76,
      "y": 36,
      "width": 1384,
      "height": 744,
      "layout": {
        "type": "dock-h",
        "children": [
          {
            "width": 296.1750183105469,
            "height": 628.2000122070312,
            "type": "dock-v",
            "children": [
              {
                "width": 296.1750183105469,
                "height": 301.0625,
                "type": "panel",
                "active": 0,
                "children": [
                  "hierarchy"
                ]
              },
              {
                "width": 296.1750183105469,
                "height": 324.13751220703125,
                "type": "panel",
                "active": 0,
                "children": [
                  "assets"
                ]
              }
            ]
          },
          {
            "width": 758,
            "height": 628.2000122070312,
            "type": "dock-v",
            "children": [
              {
                "width": 758,
                "height": 351.2375183105469,
                "type": "panel",
                "active": 0,
                "children": [
                  "scene"
                ]
              },
              {
                "width": 758,
                "height": 273.9624938964844,
                "type": "panel",
                "active": 0,
                "children": [
                  "console",
                  "timeline",
                  "game-window"
                ]
              }
            ]
          },
          {
            "width": 310.2250061035156,
            "height": 628.2000122070312,
            "type": "panel",
            "active": 0,
            "children": [
              "inspector",
              "cocos-services"
            ]
          }
        ]
      },
      "panels": [
        "hierarchy",
        "assets",
        "scene",
        "console",
        "timeline",
        "game-window",
        "inspector",
        "cocos-services"
      ]
    },
    " common-asset-worker-worker": {}
  },
  "panels": {
    "project-settings": {
      "x": 395,
      "y": 84,
      "width": 600,
      "height": 565
    }
  },
  "panelLabelWidth": {}
}
